gsimplify/__init__.py
gsimplify/auth.py
gsimplify/build.py
gsimplify/docs.py
gsimplify/drive.py
gsimplify/templates.py
gsimplify/typedefs.py
gsimplify-0.1.17.dist-info/LICENSE
gsimplify-0.1.17.dist-info/WHEEL
gsimplify-0.1.17.dist-info/METADATA
gsimplify-0.1.17.dist-info/RECORD
