Metadata-Version: 2.1
Name: gsimplify
Version: 0.1.17
Summary: 
Home-page: https://github.com/ChoateProgrammingUnion/simplify
License: MIT
Author: echapman2022
Author-email: ethan.chapman0@outlook.com
Requires-Python: >=3.6
Classifier: License :: OSI Approved :: MIT License
Classifier: Programming Language :: Python :: 3
Classifier: Programming Language :: Python :: 3.6
Classifier: Programming Language :: Python :: 3.7
Classifier: Programming Language :: Python :: 3.8
Requires-Dist: Jinja2 (>=2.11.2,<3.0.0)
Requires-Dist: gitpython (>=3.1.11,<4.0.0)
Requires-Dist: google-api-python-client (>=1.12.5,<2.0.0)
Requires-Dist: google-auth-httplib2 (>=0.0.4,<0.0.5)
Requires-Dist: google-auth-oauthlib (>=0.4.2,<0.5.0)
Requires-Dist: pydantic (>=1.7.2,<2.0.0)
Requires-Dist: tqdm (>=4.53.0,<5.0.0)
Project-URL: Repository, https://github.com/ChoateProgrammingUnion/simplify
